{
  "type": "minecraft:entity",
  "pools": [
    {
      "rolls": 1,
      "entries": [
        {
          "type": "minecraft:item",
		  "name": "minecraft:wheat_seeds",
          "functions": [
		    {
			  "function": "minecraft:set_name",
			  "name": {"translate":"item.cook.grain_seeds","italic":false}
			},
			{
			  "function": "minecraft:set_lore",
			  "lore": [
			    [{"italic":false,"color":"dark_green","translate":"lore.cook.climate"}],
			    [{"italic":false,"color":"gray","translate":"lore.cook.mild",	"with":[{"translate":"item.minecraft.wheat"}]}],
			    [{"italic":false,"color":"gray","translate":"lore.cook.humid",	"with":[{"translate":"item.cook.rice"}]}],
			    [{"italic":false,"color":"gray","translate":"lore.cook.arid",	"with":[{"translate":"item.cook.corn"}]}],
			    [{"italic":false,"color":"gray","translate":"lore.cook.artic",	"with":[{"translate":"item.cook.barley"}]}]
			  ]
			},
			{
              "function": "minecraft:set_nbt",
              "tag":"{cook:{type:3b,raw:1b,food:0, mixing:1b, roasting:1b,boiling:1b,frying:1b, color:{red:0,green:226,blue:16},base_name:'{\"translate\":\"item.cook.grain_seeds\",\"italic\":false}'}, cooked:{ id:\"minecraft:tropical_fish\",tag:{CustomModelData:6429562,cook:{food:1,redux:[1,0]}} } }"
            }
          ]
        }
      ]
    }
  ]
}